MANIFEST.in
README
setup.py
docs/changes.rst
gtfsni/__init__.py
gtfsni/generate_metro_stops.py
gtfsni/gtfs_feed_generator.py
gtfsni/gtfs_feed_validator.py
gtfsni/gtfs_schedule_viewer.py
gtfsni/kmlwriter.py
gtfsni/utils.py
gtfsni.egg-info/PKG-INFO
gtfsni.egg-info/SOURCES.txt
gtfsni.egg-info/dependency_links.txt
gtfsni.egg-info/entry_points.txt
gtfsni.egg-info/top_level.txt
gtfsni/data/translink/agency.csv
gtfsni/data/translink/metro_stops_fixes.csv
gtfsni/data/translink/opentranslink_stops.csv