Metadata-Version: 1.1
Name: gtfsni
Version: 0.0.4
Summary: Unofficial Google Transit Feed Generator for Northern Ireland.
Home-page: https://github.com/devopsni/gtfsni
Author: Jord Flanagan
Author-email: contact@devopsni.com
License: UNKNOWN
Download-URL: http://pypi.python.org/packages/source/g/gtfsni/gtfsni-0.0.4.tar.gz
Platform: UNKNOWN
